vero/__init__.py
vero/evaluator/__init__.py
vero/evaluator/evaluator.py
vero/metrics/__init__.py
vero/metrics/metric_base.py
vero/metrics/align_score/__init__.py
vero/metrics/align_score/align_score.py
vero/metrics/align_score/alignscore/__init__.py
vero/metrics/align_score/alignscore/alignscorer.py
vero/metrics/align_score/alignscore/inference.py
vero/metrics/align_score/alignscore/model.py
vero/metrics/bart_score/__init__.py
vero/metrics/bart_score/bart_score.py
vero/metrics/bart_score/bartscore/__init__.py
vero/metrics/bart_score/bartscore/bartscore.py
vero/metrics/bert_score/__init__.py
vero/metrics/bert_score/bert_score.py
vero/metrics/bleurt_score/__init__.py
vero/metrics/bleurt_score/bleurt_score.py
vero/metrics/bleurt_score/bleurt_pytorch/__init__.py
vero/metrics/bleurt_score/bleurt_pytorch/bleurt/__init__.py
vero/metrics/bleurt_score/bleurt_pytorch/bleurt/configuration_bleurt.py
vero/metrics/bleurt_score/bleurt_pytorch/bleurt/modeling_bleurt.py
vero/metrics/bleurt_score/bleurt_pytorch/bleurt/tokenization_bleurt.py
vero/metrics/bleurt_score/bleurt_pytorch/bleurt/tokenization_bleurt_fast.py
vero/metrics/bleurt_score/bleurt_pytorch/bleurt/tokenization_bleurt_sp.py
vero/metrics/bleurt_score/bleurt_pytorch/utils/__init__.py
vero/metrics/bleurt_score/bleurt_pytorch/utils/convert_tf_to_pytorch_bleurt.py
vero/metrics/citation_score/__init__.py
vero/metrics/citation_score/citation_score.py
vero/metrics/cumulative_ndcg/__init__.py
vero/metrics/cumulative_ndcg/cumulative_ndcg.py
vero/metrics/domain_overlap_score/__init__.py
vero/metrics/domain_overlap_score/domain_overlap_score.py
vero/metrics/g_eval/__init__.py
vero/metrics/g_eval/g_eval.py
vero/metrics/mean_average_precision/__init__.py
vero/metrics/mean_average_precision/mean_average_precision.py
vero/metrics/mean_reciprocal_rank/__init__.py
vero/metrics/mean_reciprocal_rank/mean_reciprocal_rank.py
vero/metrics/numerical_hallucination_score/__init__.py
vero_eval-0.0.1.6.dist-info/METADATA
vero_eval-0.0.1.6.dist-info/WHEEL
vero_eval-0.0.1.6.dist-info/licenses/LICENSE
vero_eval-0.0.1.6.dist-info/RECORD
