Metadata-Version: 2.4
Name: vero-eval
Version: 0.0.1.6
Summary: The End-to-End LLM Evaluation Framework
Project-URL: repository, https://github.com/vero-labs-ai/vero-eval.git
Project-URL: homepage, https://vero.co.in
Maintainer-email: Vishal Srivastava <vishalsrivastava8203@gmail.com>, Alakh Agrawal <alakhagr@gmail.com>
License-Expression: Apache-2.0
License-File: LICENSE
Classifier: Operating System :: OS Independent
Classifier: Programming Language :: Python :: 3
Requires-Python: >=3.9
Requires-Dist: accelerate
Requires-Dist: apscheduler
Requires-Dist: bert-score
Requires-Dist: fastapi
Requires-Dist: hf-xet
Requires-Dist: langchain
Requires-Dist: langchain-community
Requires-Dist: langchain-core
Requires-Dist: langchain-openai
Requires-Dist: langgraph
Requires-Dist: numpy
Requires-Dist: pandas
Requires-Dist: protobuf
Requires-Dist: pypdf
Requires-Dist: pytorch-lightning
Requires-Dist: rouge-score
Requires-Dist: scikit-learn
Requires-Dist: sentence-transformers
Requires-Dist: sentencepiece
Requires-Dist: spacy
Requires-Dist: tiktoken
Requires-Dist: torch
Requires-Dist: tqdm
Requires-Dist: transformers
